pelican/plugins/minifier/__init__.py
pelican/plugins/minifier/plugin.py
pelican_minifier-0.1.0.dist-info/licenses/LICENSE
pelican_minifier-0.1.0.dist-info/METADATA
pelican_minifier-0.1.0.dist-info/WHEEL
pelican_minifier-0.1.0.dist-info/entry_points.txt
pelican_minifier-0.1.0.dist-info/top_level.txt
pelican_minifier-0.1.0.dist-info/RECORD
