Metadata-Version: 2.4
Name: pelican-minifier
Version: 0.1.0
Summary: Minifies HTML, CSS, JS, and JSON in Pelican's output folder
Author-email: Vishal Chopra <digital.bill85@protonmail.com>
License: MIT
Project-URL: Homepage, https://github.com/layoutshub/pelican-minifier
Project-URL: Documentation, https://layoutshub.github.io/pelican-minifier-plugin.html
Requires-Python: >=3.7
License-File: LICENSE
Requires-Dist: pelican>=4.5
Requires-Dist: htmlmin
Requires-Dist: csscompressor
Requires-Dist: rjsmin
Requires-Dist: beautifulsoup4
Dynamic: license-file
